fastapi_repository/__init__.py
fastapi_repository/base.py
fastapi_repository-0.1.0.dist-info/METADATA
fastapi_repository-0.1.0.dist-info/WHEEL
fastapi_repository-0.1.0.dist-info/top_level.txt
fastapi_repository-0.1.0.dist-info/RECORD
