Metadata-Version: 2.4
Name: fastapi-repository
Version: 0.1.0
Summary: A base repository for FastAPI projects, inspired by Ruby on Rails' Active Record and Ransack.
Author-email: Peter Seiya Takahashi <seiya4@icloud.com>
Project-URL: Homepage, https://github.com/seiyat/fastapi-repository
Project-URL: Bug Tracker, https://github.com/seiyat/fastapi-repository/issues
Classifier: Programming Language :: Python :: 3
Classifier: License :: OSI Approved :: MIT License
Classifier: Operating System :: OS Independent
Requires-Python: >=3.8
Requires-Dist: sqlalchemy>=1.4.0
Requires-Dist: fastapi>=0.70.0
